CHANGES.rst
CONTRIBUTORS.rst
MANIFEST.in
Makefile
README.rst
bootstrap-buildout.py
buildout.cfg
setup.py
collective/__init__.py
collective.recipe.buildoutcache.egg-info/PKG-INFO
collective.recipe.buildoutcache.egg-info/SOURCES.txt
collective.recipe.buildoutcache.egg-info/dependency_links.txt
collective.recipe.buildoutcache.egg-info/entry_points.txt
collective.recipe.buildoutcache.egg-info/namespace_packages.txt
collective.recipe.buildoutcache.egg-info/not-zip-safe
collective.recipe.buildoutcache.egg-info/requires.txt
collective.recipe.buildoutcache.egg-info/top_level.txt
collective/recipe/__init__.py
collective/recipe/buildoutcache/__init__.py
collective/recipe/buildoutcache/package_list.py
collective/recipe/buildoutcache/run.py
collective/recipe/buildoutcache/testing.py
collective/recipe/buildoutcache/update_packages.py
collective/recipe/buildoutcache/tests/__init__.py
collective/recipe/buildoutcache/tests/test_run.py
collective/recipe/buildoutcache/tests/test_setup.py
docs/LICENSE.GPL
docs/LICENSE.ZPL
docs/LICENSE.txt