Metadata-Version: 1.1
Name: collective.recipe.buildoutcache
Version: 1.0.1
Summary: Recipe for generate buildout-cache.tar.gz2
Home-page: https://github.com/collective/collective.recipe.buildoutcache
Author: Benoît Suttor
Author-email: bsuttor@imio.be
License: gpl
Keywords: Plone Buildout Recipe Buildout-Cache Python
Platform: UNKNOWN
Classifier: Framework :: Buildout
Classifier: Intended Audience :: Developers
Classifier: Topic :: Software Development :: Build Tools
